free_llm_toolbox/__init__.py
free_llm_toolbox/image_classifier_utils.py
free_llm_toolbox/internet_searcher_utils.py
free_llm_toolbox/language_model.py
free_llm_toolbox/text_classifier_utils.py
free_llm_toolbox/vision_utils.py
free_llm_toolbox/prompts/llm_image_classification_index.txt
free_llm_toolbox/prompts/llm_image_classification_name.txt
free_llm_toolbox/prompts/llm_text_classification_index.txt
free_llm_toolbox/prompts/llm_text_classification_name.txt
free_llm_toolbox-0.1.9.dist-info/METADATA
free_llm_toolbox-0.1.9.dist-info/WHEEL
free_llm_toolbox-0.1.9.dist-info/licenses/LICENSE
free_llm_toolbox-0.1.9.dist-info/RECORD
