Metadata-Version: 2.4
Name: free_llm_toolbox
Version: 0.1.9
Summary: A Python toolbox for easy interaction with various LLMs and Vision models
Project-URL: Homepage, https://github.com/username/free_llm_toolbox
Project-URL: Repository, https://github.com/username/free_llm_toolbox
Author: Yanis112
License-Expression: MIT
License-File: LICENSE
Keywords: ai,llm,machine-learning,text-generation,vision
Classifier: Development Status :: 4 - Beta
Classifier: Intended Audience :: Developers
Classifier: License :: OSI Approved :: MIT License
Classifier: Programming Language :: Python :: 3
Classifier: Programming Language :: Python :: 3.8
Classifier: Programming Language :: Python :: 3.9
Classifier: Programming Language :: Python :: 3.10
Classifier: Programming Language :: Python :: 3.11
Requires-Python: >=3.10
Requires-Dist: build>=1.2.2.post1
Requires-Dist: google-generativeai>=0.3.0
Requires-Dist: groq>=0.4.0
Requires-Dist: jsonschema==3.2.0
Requires-Dist: langchain-cerebras>=0.5.0
Requires-Dist: langchain-community>=0.3.18
Requires-Dist: langchain-core>=0.1.0
Requires-Dist: langchain-google-genai>=2.0.10
Requires-Dist: langchain-groq>=0.2.4
Requires-Dist: langchain-ollama>=0.2.3
Requires-Dist: langchain>=0.1.0
Requires-Dist: ollama>=0.4.7
Requires-Dist: pillow>=9.0.0
Requires-Dist: pydantic>=2.0.0
Requires-Dist: pytest>=8.3.4
Requires-Dist: python-dotenv>=0.19.0
Requires-Dist: torch>=2.0.0
Requires-Dist: transformers>=4.0.0
Requires-Dist: twine>=6.1.0
Provides-Extra: dev
Requires-Dist: black>=23.0; extra == 'dev'
Requires-Dist: isort>=5.0; extra == 'dev'
Requires-Dist: pytest-cov>=4.0; extra == 'dev'
Requires-Dist: pytest>=7.0; extra == 'dev'
